channelstream/__init__.py
channelstream/channel.py
channelstream/connection.py
channelstream/events.py
channelstream/exceptions.py
channelstream/gc.py
channelstream/operations.py
channelstream/patched_json.py
channelstream/policy_server.py
channelstream/server_state.py
channelstream/subscribers.py
channelstream/user.py
channelstream/utils.py
channelstream/ws_app.py
channelstream/wsgi_app.py
channelstream/cli/__init__.py
channelstream/cli/start.py
channelstream/cli/utils.py
channelstream/static/channelstream-admin.js
channelstream/static/@babel/polyfill/browser.js
channelstream/static/@babel/polyfill/noConflict.js
channelstream/static/@babel/polyfill/dist/polyfill.js
channelstream/static/@babel/polyfill/dist/polyfill.min.js
channelstream/static/@babel/polyfill/lib/index.js
channelstream/static/@babel/polyfill/lib/noConflict.js
channelstream/static/channelstream/channelstream.js
channelstream/static/channelstream/index.js
channelstream/static/channelstream/sha-esm.js
channelstream/static/channelstream/sha.js
channelstream/static/channelstream/sha1-esm.js
channelstream/static/channelstream/sha1.js
channelstream/static/channelstream/signer.js
channelstream/templates/admin.jinja2
channelstream/templates/admin_layout.jinja2
channelstream/templates/explorer.jinja2
channelstream/templates/sign_in.jinja2
channelstream/templates/ini/channelstream.ini.jinja2
channelstream/validation/__init__.py
channelstream/validation/schemas.py
channelstream/wsgi_views/__init__.py
channelstream/wsgi_views/error_handlers.py
channelstream/wsgi_views/server.py
channelstream/wsgi_views/wsgi_security.py
channelstream-0.7.1.dist-info/LICENSE
channelstream-0.7.1.dist-info/METADATA
channelstream-0.7.1.dist-info/WHEEL
channelstream-0.7.1.dist-info/entry_points.txt
channelstream-0.7.1.dist-info/top_level.txt
channelstream-0.7.1.dist-info/zip-safe
channelstream-0.7.1.dist-info/RECORD
