Metadata-Version: 2.1
Name: channelstream
Version: 0.7.1
Summary: Websocket server supporting channels/users communication
Home-page: https://github.com/Channelstream/channelstream
Author: Marcin Lulek
Author-email: info@webreactor.eu
License: BSD
Keywords: websockets async communication chat notification django flask pyramid
Platform: UNKNOWN
Classifier: Framework :: Django
Classifier: Framework :: Flask
Classifier: Framework :: Pyramid
Classifier: Intended Audience :: Developers
Classifier: License :: OSI Approved :: BSD License
Classifier: Programming Language :: Python :: 3
Classifier: Programming Language :: Python :: 3.6
Classifier: Programming Language :: Python :: 3.7
Classifier: Programming Language :: Python :: 3.8
Classifier: Topic :: Internet :: WWW/HTTP
Classifier: Topic :: Communications :: Chat
Classifier: Topic :: Communications :: Conferencing
Requires-Python: >=3.6
Requires-Dist: gevent (>=1.3.7)
Requires-Dist: itsdangerous (==1.1.0)
Requires-Dist: marshmallow (<3.0.0,==2.18.0)
Requires-Dist: pyramid (>=1.9.2)
Requires-Dist: pyramid-apispec (==0.3.3)
Requires-Dist: pyramid-jinja2 (>=2.7)
Requires-Dist: python-dateutil (>=2.7.5)
Requires-Dist: requests (>=2.20.0)
Requires-Dist: ws4py (>=0.5.1)
Provides-Extra: dev
Requires-Dist: coverage ; extra == 'dev'
Requires-Dist: mock ; extra == 'dev'
Requires-Dist: mypy ; extra == 'dev'
Requires-Dist: pyramid ; extra == 'dev'
Requires-Dist: pytest ; extra == 'dev'
Requires-Dist: tox ; extra == 'dev'
Requires-Dist: webtest ; extra == 'dev'
Provides-Extra: lint
Requires-Dist: black ; extra == 'lint'
